tu4c/__init__.py
tu4c/models/LeNet.py
tu4c/models/__init__.py
tu4c/models/config.py
tu4c/utils/__init__.py
tu4c/utils/common_utils.py
tu4c-0.0.0.dist-info/LICENSE
tu4c-0.0.0.dist-info/METADATA
tu4c-0.0.0.dist-info/WHEEL
tu4c-0.0.0.dist-info/top_level.txt
tu4c-0.0.0.dist-info/RECORD
