Metadata-Version: 2.1
Name: tu4c
Version: 0.0.0
Summary: torch utils for city945
Home-page: https://github.com/city945
Author: city945
Author-email: city945@njust.edu.cn
Classifier: Programming Language :: Python :: 3
Classifier: License :: OSI Approved :: GNU General Public License v3 (GPLv3)
Classifier: Operating System :: OS Independent
License-File: LICENSE
